LICENSE
MANIFEST.in
README.rst
setup.py
sample/__init__.py
sample/core.py
sample/helpers.py
throw_away_sample.egg-info/PKG-INFO
throw_away_sample.egg-info/SOURCES.txt
throw_away_sample.egg-info/dependency_links.txt
throw_away_sample.egg-info/top_level.txt