Metadata-Version: 1.0
Name: throw-away-sample
Version: 0.1.1
Summary: Sample package for Python-Guide.org
Home-page: https://github.com/kennethreitz/samplemod
Author: Kenneth Reitz
Author-email: me@kennethreitz.com
License: Copyright (c) 2012, Kenneth Reitz
